leicaexperiment/__init__.py
leicaexperiment/experiment.py
leicaexperiment/utils.py
leicaexperiment/VERSION
leicaexperiment-0.2.0.dist-info/DESCRIPTION.rst
leicaexperiment-0.2.0.dist-info/METADATA
leicaexperiment-0.2.0.dist-info/metadata.json
leicaexperiment-0.2.0.dist-info/RECORD
leicaexperiment-0.2.0.dist-info/top_level.txt
leicaexperiment-0.2.0.dist-info/WHEEL
