Metadata-Version: 2.0
Name: leicaexperiment
Version: 0.2.0
Summary: Read, stitch and compress Leica LAS Matrix Screener experiments
Home-page: https://github.com/arve0/leicaexperiment
Author: Arve Seljebu
Author-email: arve.seljebu@gmail.com
License: MIT
Keywords: leicaexperiment
Platform: UNKNOWN
Classifier: Development Status :: 2 - Pre-Alpha
Classifier: Intended Audience :: Developers
Classifier: License :: OSI Approved :: MIT License
Classifier: Natural Language :: English
Classifier: Programming Language :: Python :: 2
Classifier: Programming Language :: Python :: 2.7
Classifier: Programming Language :: Python :: 3
Classifier: Programming Language :: Python :: 3.4
Classifier: Programming Language :: Python :: Implementation :: PyPy
Requires-Dist: pydebug
Requires-Dist: Pillow
Requires-Dist: fijibin
Requires-Dist: lxml
Requires-Dist: joblib
